sqlframe/__init__.py
sqlframe/_version.py
sqlframe/py.typed
sqlframe/base/__init__.py
sqlframe/base/_typing.py
sqlframe/base/catalog.py
sqlframe/base/column.py
sqlframe/base/dataframe.py
sqlframe/base/decorators.py
sqlframe/base/exceptions.py
sqlframe/base/function_alternatives.py
sqlframe/base/functions.py
sqlframe/base/group.py
sqlframe/base/normalize.py
sqlframe/base/operations.py
sqlframe/base/readerwriter.py
sqlframe/base/session.py
sqlframe/base/table.py
sqlframe/base/transforms.py
sqlframe/base/types.py
sqlframe/base/udf.py
sqlframe/base/util.py
sqlframe/base/window.py
sqlframe/base/mixins/__init__.py
sqlframe/base/mixins/catalog_mixins.py
sqlframe/base/mixins/dataframe_mixins.py
sqlframe/base/mixins/readwriter_mixins.py
sqlframe/base/mixins/table_mixins.py
sqlframe/bigquery/__init__.py
sqlframe/bigquery/catalog.py
sqlframe/bigquery/column.py
sqlframe/bigquery/dataframe.py
sqlframe/bigquery/functions.py
sqlframe/bigquery/functions.pyi
sqlframe/bigquery/group.py
sqlframe/bigquery/readwriter.py
sqlframe/bigquery/session.py
sqlframe/bigquery/table.py
sqlframe/bigquery/types.py
sqlframe/bigquery/udf.py
sqlframe/bigquery/window.py
sqlframe/databricks/__init__.py
sqlframe/databricks/catalog.py
sqlframe/databricks/column.py
sqlframe/databricks/dataframe.py
sqlframe/databricks/functions.py
sqlframe/databricks/functions.pyi
sqlframe/databricks/group.py
sqlframe/databricks/readwriter.py
sqlframe/databricks/session.py
sqlframe/databricks/table.py
sqlframe/databricks/types.py
sqlframe/databricks/udf.py
sqlframe/databricks/window.py
sqlframe/duckdb/__init__.py
sqlframe/duckdb/catalog.py
sqlframe/duckdb/column.py
sqlframe/duckdb/dataframe.py
sqlframe/duckdb/functions.py
sqlframe/duckdb/functions.pyi
sqlframe/duckdb/group.py
sqlframe/duckdb/readwriter.py
sqlframe/duckdb/session.py
sqlframe/duckdb/table.py
sqlframe/duckdb/types.py
sqlframe/duckdb/udf.py
sqlframe/duckdb/window.py
sqlframe/postgres/__init__.py
sqlframe/postgres/catalog.py
sqlframe/postgres/column.py
sqlframe-3.45.0.dist-info/LICENSE
sqlframe-3.45.0.dist-info/METADATA
sqlframe-3.45.0.dist-info/WHEEL
sqlframe-3.45.0.dist-info/top_level.txt
sqlframe-3.45.0.dist-info/RECORD
